snowflake_id_toolkit/__init__.py
snowflake_id_toolkit/_config.py
snowflake_id_toolkit/_exceptions.py
snowflake_id_toolkit/_generator.py
snowflake_id_toolkit/_id.py
snowflake_id_toolkit/py.typed
snowflake_id_toolkit/instagram/__init__.py
snowflake_id_toolkit/instagram/_config.py
snowflake_id_toolkit/instagram/_generator.py
snowflake_id_toolkit/instagram/_id.py
snowflake_id_toolkit/sony/__init__.py
snowflake_id_toolkit/sony/_config.py
snowflake_id_toolkit/sony/_generator.py
snowflake_id_toolkit/sony/_id.py
snowflake_id_toolkit/twitter/__init__.py
snowflake_id_toolkit/twitter/_config.py
snowflake_id_toolkit/twitter/_generator.py
snowflake_id_toolkit/twitter/_id.py
snowflake_id_toolkit-0.6.0.dist-info/METADATA
snowflake_id_toolkit-0.6.0.dist-info/WHEEL
snowflake_id_toolkit-0.6.0.dist-info/licenses/LICENSE
snowflake_id_toolkit-0.6.0.dist-info/RECORD
