Metadata-Version: 2.4
Name: snowflake-id-toolkit
Version: 0.6.0
Summary: Python toolkit for generating Twitter Snowflake & Sonyflake IDs
Project-URL: Homepage, https://github.com/pavelprokhorenko/snowflake-id-toolkit
Project-URL: Releases, https://github.com/pavelprokhorenko/snowflake-id-toolkit/releases
Project-URL: Repository, https://github.com/pavelprokhorenko/snowflake-id-toolkit
Project-URL: Issues, https://github.com/pavelprokhorenko/snowflake-id-toolkit/issues
Author-email: Pavel Prokhorenko <prohorenkopavel74@gmail.com>
License-File: LICENSE
Keywords: distributed,generator,id,snowflake,sonyflake,unique-id
Classifier: Intended Audience :: Developers
Classifier: License :: OSI Approved :: MIT License
Classifier: Programming Language :: Python
Classifier: Programming Language :: Python :: 3
Classifier: Programming Language :: Python :: 3 :: Only
Classifier: Programming Language :: Python :: 3.10
Classifier: Programming Language :: Python :: 3.11
Classifier: Programming Language :: Python :: 3.12
Classifier: Programming Language :: Python :: 3.13
Classifier: Topic :: Software Development :: Libraries
Classifier: Topic :: Software Development :: Libraries :: Python Modules
Classifier: Typing :: Typed
Requires-Python: >=3.10
